{
	"$schema": "http://schema.management.azure.com/schemas/2015-01-01/deploymentTemplate.json#",
	"contentVersion": "1.0.0.0",
	"parameters": {
		"factoryName": {
			"type": "string",
			"metadata": "Data Factory name",
			"defaultValue": "adf-p1-prod-eus"
		}
	},
	"variables": {
		"factoryId": "[concat('Microsoft.DataFactory/factories/', parameters('factoryName'))]"
	},
	"resources": [
		{
			"name": "[concat(parameters('factoryName'), '/Parquet2')]",
			"type": "Microsoft.DataFactory/factories/datasets",
			"apiVersion": "2018-06-01",
			"properties": {
				"linkedServiceName": {
					"referenceName": "cn_dls_p1",
					"type": "LinkedServiceReference"
				},
				"annotations": [],
				"type": "Parquet",
				"typeProperties": {
					"location": {
						"type": "AzureBlobFSLocation",
						"folderPath": "output/deals",
						"fileSystem": "acr-p1-internal"
					},
					"compressionCodec": "snappy"
				},
				"schema": []
			},
			"dependsOn": []
		},
		{
			"name": "[concat(parameters('factoryName'), '/chk_trx_metadata')]",
			"type": "Microsoft.DataFactory/factories/datasets",
			"apiVersion": "2018-06-01",
			"properties": {
				"linkedServiceName": {
					"referenceName": "cn_dls_p1",
					"type": "LinkedServiceReference"
				},
				"annotations": [],
				"type": "DelimitedText",
				"typeProperties": {
					"location": {
						"type": "AzureBlobFSLocation",
						"fileName": "ext_ca_call_req.txt",
						"folderPath": "acr-p1-ca-sdm",
						"fileSystem": "acr-p1-prod-eus-001"
					},
					"columnDelimiter": "|",
					"escapeChar": "\\",
					"quoteChar": "\""
				},
				"schema": [
					{
						"type": "String"
					}
				]
			},
			"dependsOn": []
		},
		{
			"name": "[concat(parameters('factoryName'), '/dt_ca_act_log')]",
			"type": "Microsoft.DataFactory/factories/datasets",
			"apiVersion": "2018-06-01",
			"properties": {
				"linkedServiceName": {
					"referenceName": "cn_dls_p1",
					"type": "LinkedServiceReference"
				},
				"folder": {
					"name": "ca-sdm"
				},
				"annotations": [],
				"type": "DelimitedText",
				"typeProperties": {
					"location": {
						"type": "AzureBlobFSLocation",
						"fileName": "ext_ca_act_log.txt",
						"folderPath": "acr-p1-ca-sdm",
						"fileSystem": "acr-p1-prod-eus-001"
					},
					"columnDelimiter": "|",
					"escapeChar": "\\",
					"quoteChar": "\""
				},
				"schema": [
					{
						"type": "String"
					}
				]
			},
			"dependsOn": []
		},
		{
			"name": "[concat(parameters('factoryName'), '/dt_ca_call_req')]",
			"type": "Microsoft.DataFactory/factories/datasets",
			"apiVersion": "2018-06-01",
			"properties": {
				"linkedServiceName": {
					"referenceName": "cn_dls_p1",
					"type": "LinkedServiceReference"
				},
				"folder": {
					"name": "ca-sdm"
				},
				"annotations": [],
				"type": "DelimitedText",
				"typeProperties": {
					"location": {
						"type": "AzureBlobFSLocation",
						"fileName": "ext_ca_call_req.txt",
						"folderPath": "acr-p1-ca-sdm",
						"fileSystem": "acr-p1-prod-eus-001"
					},
					"columnDelimiter": "|",
					"escapeChar": "\\",
					"quoteChar": "\""
				},
				"schema": [
					{
						"type": "String"
					}
				]
			},
			"dependsOn": []
		},
		{
			"name": "[concat(parameters('factoryName'), '/dt_ca_category')]",
			"type": "Microsoft.DataFactory/factories/datasets",
			"apiVersion": "2018-06-01",
			"properties": {
				"linkedServiceName": {
					"referenceName": "cn_dls_p1",
					"type": "LinkedServiceReference"
				},
				"folder": {
					"name": "ca-sdm"
				},
				"annotations": [],
				"type": "DelimitedText",
				"typeProperties": {
					"location": {
						"type": "AzureBlobFSLocation",
						"fileName": "ext_ca_category.txt",
						"folderPath": "acr-p1-ca-sdm",
						"fileSystem": "acr-p1-prod-eus-001"
					},
					"columnDelimiter": "|",
					"escapeChar": "\\",
					"quoteChar": "\""
				},
				"schema": [
					{
						"type": "String"
					}
				]
			},
			"dependsOn": []
		},
		{
			"name": "[concat(parameters('factoryName'), '/dt_ca_company')]",
			"type": "Microsoft.DataFactory/factories/datasets",
			"apiVersion": "2018-06-01",
			"properties": {
				"linkedServiceName": {
					"referenceName": "cn_dls_p1",
					"type": "LinkedServiceReference"
				},
				"folder": {
					"name": "ca-sdm"
				},
				"annotations": [],
				"type": "DelimitedText",
				"typeProperties": {
					"location": {
						"type": "AzureBlobFSLocation",
						"fileName": "ext_ca_company.txt",
						"folderPath": "acr-p1-ca-sdm",
						"fileSystem": "acr-p1-prod-eus-001"
					},
					"columnDelimiter": "|",
					"escapeChar": "\\",
					"quoteChar": "\""
				},
				"schema": [
					{
						"type": "String"
					}
				]
			},
			"dependsOn": []
		},
		{
			"name": "[concat(parameters('factoryName'), '/dt_ca_contact')]",
			"type": "Microsoft.DataFactory/factories/datasets",
			"apiVersion": "2018-06-01",
			"properties": {
				"linkedServiceName": {
					"referenceName": "cn_dls_p1",
					"type": "LinkedServiceReference"
				},
				"folder": {
					"name": "ca-sdm"
				},
				"annotations": [],
				"type": "DelimitedText",
				"typeProperties": {
					"location": {
						"type": "AzureBlobFSLocation",
						"fileName": "ext_ca_contact.txt",
						"folderPath": "acr-p1-ca-sdm",
						"fileSystem": "acr-p1-prod-eus-001"
					},
					"columnDelimiter": "|",
					"escapeChar": "\\",
					"quoteChar": "\""
				},
				"schema": [
					{
						"type": "String"
					}
				]
			},
			"dependsOn": []
		},
		{
			"name": "[concat(parameters('factoryName'), '/dt_ca_contact_type')]",
			"type": "Microsoft.DataFactory/factories/datasets",
			"apiVersion": "2018-06-01",
			"properties": {
				"linkedServiceName": {
					"referenceName": "cn_dls_p1",
					"type": "LinkedServiceReference"
				},
				"folder": {
					"name": "ca-sdm"
				},
				"annotations": [],
				"type": "DelimitedText",
				"typeProperties": {
					"location": {
						"type": "AzureBlobFSLocation",
						"fileName": "ext_ca_contact_type.txt",
						"folderPath": "acr-p1-ca-sdm",
						"fileSystem": "acr-p1-prod-eus-001"
					},
					"columnDelimiter": "|",
					"escapeChar": "\\",
					"quoteChar": "\""
				},
				"schema": [
					{
						"type": "String"
					}
				]
			},
			"dependsOn": []
		},
		{
			"name": "[concat(parameters('factoryName'), '/dt_ca_country')]",
			"type": "Microsoft.DataFactory/factories/datasets",
			"apiVersion": "2018-06-01",
			"properties": {
				"linkedServiceName": {
					"referenceName": "cn_dls_p1",
					"type": "LinkedServiceReference"
				},
				"folder": {
					"name": "ca-sdm"
				},
				"annotations": [],
				"type": "DelimitedText",
				"typeProperties": {
					"location": {
						"type": "AzureBlobFSLocation",
						"fileName": "ext_ca_country.txt",
						"folderPath": "acr-p1-ca-sdm",
						"fileSystem": "acr-p1-prod-eus-001"
					},
					"columnDelimiter": "|",
					"escapeChar": "\\",
					"quoteChar": "\""
				},
				"schema": [
					{
						"type": "String"
					}
				]
			},
			"dependsOn": []
		},
		{
			"name": "[concat(parameters('factoryName'), '/dt_ca_crt')]",
			"type": "Microsoft.DataFactory/factories/datasets",
			"apiVersion": "2018-06-01",
			"properties": {
				"linkedServiceName": {
					"referenceName": "cn_dls_p1",
					"type": "LinkedServiceReference"
				},
				"folder": {
					"name": "ca-sdm"
				},
				"annotations": [],
				"type": "DelimitedText",
				"typeProperties": {
					"location": {
						"type": "AzureBlobFSLocation",
						"fileName": "ext_ca_crt.txt",
						"folderPath": "acr-p1-ca-sdm",
						"fileSystem": "acr-p1-prod-eus-001"
					},
					"columnDelimiter": "|",
					"escapeChar": "\\",
					"quoteChar": "\""
				},
				"schema": [
					{
						"type": "String"
					}
				]
			},
			"dependsOn": []
		},
		{
			"name": "[concat(parameters('factoryName'), '/dt_ca_impact')]",
			"type": "Microsoft.DataFactory/factories/datasets",
			"apiVersion": "2018-06-01",
			"properties": {
				"linkedServiceName": {
					"referenceName": "cn_dls_p1",
					"type": "LinkedServiceReference"
				},
				"folder": {
					"name": "ca-sdm"
				},
				"annotations": [],
				"type": "DelimitedText",
				"typeProperties": {
					"location": {
						"type": "AzureBlobFSLocation",
						"fileName": "ext_ca_impact.txt",
						"folderPath": "acr-p1-ca-sdm",
						"fileSystem": "acr-p1-prod-eus-001"
					},
					"columnDelimiter": "|",
					"escapeChar": "\\",
					"quoteChar": "\""
				},
				"schema": [
					{
						"type": "String"
					}
				]
			},
			"dependsOn": []
		},
		{
			"name": "[concat(parameters('factoryName'), '/dt_ca_location')]",
			"type": "Microsoft.DataFactory/factories/datasets",
			"apiVersion": "2018-06-01",
			"properties": {
				"linkedServiceName": {
					"referenceName": "cn_dls_p1",
					"type": "LinkedServiceReference"
				},
				"folder": {
					"name": "ca-sdm"
				},
				"annotations": [],
				"type": "DelimitedText",
				"typeProperties": {
					"location": {
						"type": "AzureBlobFSLocation",
						"fileName": "ext_ca_location.txt",
						"folderPath": "acr-p1-ca-sdm",
						"fileSystem": "acr-p1-prod-eus-001"
					},
					"columnDelimiter": "|",
					"escapeChar": "\\",
					"quoteChar": "\""
				},
				"schema": [
					{
						"type": "String"
					}
				]
			},
			"dependsOn": []
		},
		{
			"name": "[concat(parameters('factoryName'), '/dt_ca_organization')]",
			"type": "Microsoft.DataFactory/factories/datasets",
			"apiVersion": "2018-06-01",
			"properties": {
				"linkedServiceName": {
					"referenceName": "cn_dls_p1",
					"type": "LinkedServiceReference"
				},
				"folder": {
					"name": "ca-sdm"
				},
				"annotations": [],
				"type": "DelimitedText",
				"typeProperties": {
					"location": {
						"type": "AzureBlobFSLocation",
						"fileName": "ext_ca_organization.txt",
						"folderPath": "acr-p1-ca-sdm",
						"fileSystem": "acr-p1-prod-eus-001"
					},
					"columnDelimiter": "|",
					"escapeChar": "\\",
					"quoteChar": "\""
				},
				"schema": [
					{
						"type": "String"
					}
				]
			},
			"dependsOn": []
		},
		{
			"name": "[concat(parameters('factoryName'), '/dt_ca_owned_resource')]",
			"type": "Microsoft.DataFactory/factories/datasets",
			"apiVersion": "2018-06-01",
			"properties": {
				"linkedServiceName": {
					"referenceName": "cn_dls_p1",
					"type": "LinkedServiceReference"
				},
				"folder": {
					"name": "ca-sdm"
				},
				"annotations": [],
				"type": "DelimitedText",
				"typeProperties": {
					"location": {
						"type": "AzureBlobFSLocation",
						"fileName": "ext_ca_owned_resource.txt",
						"folderPath": "acr-p1-ca-sdm",
						"fileSystem": "acr-p1-prod-eus-001"
					},
					"columnDelimiter": "|",
					"escapeChar": "\\",
					"quoteChar": "\""
				},
				"schema": [
					{
						"type": "String"
					}
				]
			},
			"dependsOn": []
		},
		{
			"name": "[concat(parameters('factoryName'), '/dt_ca_resolution_code')]",
			"type": "Microsoft.DataFactory/factories/datasets",
			"apiVersion": "2018-06-01",
			"properties": {
				"description": "table = usp_resolution_code",
				"linkedServiceName": {
					"referenceName": "cn_dls_p1",
					"type": "LinkedServiceReference"
				},
				"folder": {
					"name": "ca-sdm"
				},
				"annotations": [],
				"type": "DelimitedText",
				"typeProperties": {
					"location": {
						"type": "AzureBlobFSLocation",
						"fileName": "ext_ca_resolution_code.txt",
						"folderPath": "acr-p1-ca-sdm",
						"fileSystem": "acr-p1-prod-eus-001"
					},
					"columnDelimiter": "|",
					"escapeChar": "\\",
					"quoteChar": "\""
				},
				"schema": [
					{
						"type": "String"
					}
				]
			},
			"dependsOn": []
		},
		{
			"name": "[concat(parameters('factoryName'), '/dt_ca_resource_department')]",
			"type": "Microsoft.DataFactory/factories/datasets",
			"apiVersion": "2018-06-01",
			"properties": {
				"linkedServiceName": {
					"referenceName": "cn_dls_p1",
					"type": "LinkedServiceReference"
				},
				"folder": {
					"name": "ca-sdm"
				},
				"annotations": [],
				"type": "DelimitedText",
				"typeProperties": {
					"location": {
						"type": "AzureBlobFSLocation",
						"fileName": "ext_ca_resource_department.txt",
						"folderPath": "acr-p1-ca-sdm",
						"fileSystem": "acr-p1-prod-eus-001"
					},
					"columnDelimiter": "|",
					"escapeChar": "\\",
					"quoteChar": "\""
				},
				"schema": [
					{
						"type": "String"
					}
				]
			},
			"dependsOn": []
		},
		{
			"name": "[concat(parameters('factoryName'), '/dt_ca_status')]",
			"type": "Microsoft.DataFactory/factories/datasets",
			"apiVersion": "2018-06-01",
			"properties": {
				"linkedServiceName": {
					"referenceName": "cn_dls_p1",
					"type": "LinkedServiceReference"
				},
				"folder": {
					"name": "ca-sdm"
				},
				"annotations": [],
				"type": "DelimitedText",
				"typeProperties": {
					"location": {
						"type": "AzureBlobFSLocation",
						"fileName": "ext_ca_status.txt",
						"folderPath": "acr-p1-ca-sdm",
						"fileSystem": "acr-p1-prod-eus-001"
					},
					"columnDelimiter": "|",
					"escapeChar": "\\",
					"quoteChar": "\""
				},
				"schema": [
					{
						"type": "String"
					}
				]
			},
			"dependsOn": []
		},
		{
			"name": "[concat(parameters('factoryName'), '/dt_ca_tenant')]",
			"type": "Microsoft.DataFactory/factories/datasets",
			"apiVersion": "2018-06-01",
			"properties": {
				"linkedServiceName": {
					"referenceName": "cn_dls_p1",
					"type": "LinkedServiceReference"
				},
				"folder": {
					"name": "ca-sdm"
				},
				"annotations": [],
				"type": "DelimitedText",
				"typeProperties": {
					"location": {
						"type": "AzureBlobFSLocation",
						"fileName": "ext_ca_tenant.txt",
						"folderPath": "acr-p1-ca-sdm",
						"fileSystem": "acr-p1-prod-eus-001"
					},
					"columnDelimiter": "|",
					"escapeChar": "\\",
					"quoteChar": "\""
				},
				"schema": [
					{
						"type": "String"
					}
				]
			},
			"dependsOn": []
		},
		{
			"name": "[concat(parameters('factoryName'), '/dt_casdm_call_req')]",
			"type": "Microsoft.DataFactory/factories/datasets",
			"apiVersion": "2018-06-01",
			"properties": {
				"linkedServiceName": {
					"referenceName": "cn_dls_p1",
					"type": "LinkedServiceReference"
				},
				"annotations": [],
				"type": "Parquet",
				"typeProperties": {
					"location": {
						"type": "AzureBlobFSLocation",
						"fileName": "teste.parquet",
						"folderPath": "acr-p1-ca-sdm/",
						"fileSystem": "acr-p1-prod-eus-001"
					},
					"compressionCodec": "snappy"
				},
				"schema": []
			},
			"dependsOn": []
		},
		{
			"name": "[concat(parameters('factoryName'), '/dt_dyn_opp')]",
			"type": "Microsoft.DataFactory/factories/datasets",
			"apiVersion": "2018-06-01",
			"properties": {
				"linkedServiceName": {
					"referenceName": "cn_dls_p1",
					"type": "LinkedServiceReference"
				},
				"folder": {
					"name": "ca-sdm"
				},
				"annotations": [],
				"type": "DelimitedText",
				"typeProperties": {
					"location": {
						"type": "AzureBlobFSLocation",
						"fileName": "ext_dyn_opp.txt",
						"folderPath": "acr-p1-ca-sdm",
						"fileSystem": "acr-p1-prod-eus-001"
					},
					"columnDelimiter": "|",
					"escapeChar": "\\",
					"quoteChar": "\""
				},
				"schema": [
					{
						"type": "String"
					}
				]
			},
			"dependsOn": []
		}
	]
}